Metadata-Version: 2.1
Name: flask-mongoengine-tschaume
Version: 1.1.0
Summary: Flask extension that provides integration with MongoEngine and WTF model forms.
Author-email: Ross Lawley <ross.lawley@gmail.com>
Maintainer-email: Andrey Shpak <ashpak@ashpak.ru>, Patrick Huck <phuck@lbl.gov>
License: BSD 3-Clause License
Project-URL: Homepage, https://github.com/tschaume/flask-mongoengine
Project-URL: Documentation, http://docs.mongoengine.org/projects/flask-mongoengine/en/latest/
Project-URL: Repository, https://github.com/tschaume/flask-mongoengine
Project-URL: Changelog, https://github.com/tschaume/flask-mongoengine/releases
Keywords: flask,wtf,wtf-forms,forms,mongo,pymongo,mongoengine,extension
Platform: any
Classifier: Development Status :: 4 - Beta
Classifier: Environment :: Web Environment
Classifier: Intended Audience :: Developers
Classifier: License :: OSI Approved :: BSD License
Classifier: Operating System :: OS Independent
Classifier: Programming Language :: Python
Classifier: Programming Language :: Python :: 3 :: Only
Classifier: Programming Language :: Python :: 3
Classifier: Programming Language :: Python :: 3.7
Classifier: Programming Language :: Python :: 3.8
Classifier: Programming Language :: Python :: 3.9
Classifier: Programming Language :: Python :: 3.10
Classifier: Programming Language :: Python :: Implementation :: PyPy
Classifier: Programming Language :: Python :: Implementation :: CPython
Classifier: Topic :: Internet :: WWW/HTTP :: Dynamic Content
Classifier: Topic :: Software Development :: Libraries :: Python Modules
Classifier: Framework :: Flask
Requires-Python: >=3.7
License-File: LICENSE.md
License-File: AUTHORS.md
Requires-Dist: Flask (>=1.1.4)
Requires-Dist: mongoengine (>=0.21)
Requires-Dist: importlib-metadata ; python_version < "3.8"
Provides-Extra: dev
Requires-Dist: black (==22.6.0) ; extra == 'dev'
Requires-Dist: pre-commit ; extra == 'dev'
Requires-Dist: pytest ; extra == 'dev'
Requires-Dist: pytest-cov ; extra == 'dev'
Requires-Dist: pytest-mock ; extra == 'dev'
Requires-Dist: nox ; extra == 'dev'
Requires-Dist: Pillow (>=7.0.0) ; extra == 'dev'
Requires-Dist: blinker ; extra == 'dev'
Provides-Extra: legacy
Requires-Dist: MarkupSafe (==2.0.1) ; extra == 'legacy'
Provides-Extra: legacy-dev
Requires-Dist: pytest ; extra == 'legacy-dev'
Requires-Dist: pytest-cov ; extra == 'legacy-dev'
Requires-Dist: pytest-mock ; extra == 'legacy-dev'
Requires-Dist: Pillow (>=7.0.0) ; extra == 'legacy-dev'
Requires-Dist: blinker ; extra == 'legacy-dev'
Provides-Extra: toolbar
Requires-Dist: Flask-DebugToolbar (>=0.11.0) ; extra == 'toolbar'
Provides-Extra: wtf
Requires-Dist: WTForms[email] (>=3.0.0) ; extra == 'wtf'
Requires-Dist: Flask-WTF (>=0.14.3) ; extra == 'wtf'
